mahesh/__init__.py
mahesh/maheshg.py
express_love-0.0.1.dist-info/METADATA
express_love-0.0.1.dist-info/WHEEL
express_love-0.0.1.dist-info/top_level.txt
express_love-0.0.1.dist-info/RECORD
